odoo/addons/stock_picking_product_availability_inline/README.rst
odoo/addons/stock_picking_product_availability_inline/__init__.py
odoo/addons/stock_picking_product_availability_inline/__manifest__.py
odoo/addons/stock_picking_product_availability_inline/i18n/it.po
odoo/addons/stock_picking_product_availability_inline/i18n/stock_picking_product_availability_inline.pot
odoo/addons/stock_picking_product_availability_inline/models/__init__.py
odoo/addons/stock_picking_product_availability_inline/models/product_product.py
odoo/addons/stock_picking_product_availability_inline/models/stock_picking.py
odoo/addons/stock_picking_product_availability_inline/readme/CONTRIBUTORS.md
odoo/addons/stock_picking_product_availability_inline/readme/DESCRIPTION.md
odoo/addons/stock_picking_product_availability_inline/readme/USAGE.md
odoo/addons/stock_picking_product_availability_inline/static/description/icon.png
odoo/addons/stock_picking_product_availability_inline/static/description/index.html
odoo/addons/stock_picking_product_availability_inline/tests/__init__.py
odoo/addons/stock_picking_product_availability_inline/tests/test_stock_picking_product_availability_inline.py
odoo/addons/stock_picking_product_availability_inline/views/stock_move_line_views.xml
odoo/addons/stock_picking_product_availability_inline/views/stock_picking_views.xml
odoo_addon_stock_picking_product_availability_inline-18.0.1.0.0.4.dist-info/METADATA
odoo_addon_stock_picking_product_availability_inline-18.0.1.0.0.4.dist-info/WHEEL
odoo_addon_stock_picking_product_availability_inline-18.0.1.0.0.4.dist-info/top_level.txt
odoo_addon_stock_picking_product_availability_inline-18.0.1.0.0.4.dist-info/RECORD
